aimapper/__init__.py
aimapper-0.1.0.dist-info/WHEEL
aimapper-0.1.0.dist-info/METADATA
aimapper-0.1.0.dist-info/RECORD
